[
    {
        "arrStrings": [
            {
                "nameDeal": "Приход",
                "nameWhoGive": "Люльков Андрей",
                "nameWhoTake": "ООО Молодость",
                "summ": 1999,
                "comment": "оплата за заказ №231",
                "date": "2019-01-21T23:01:15.630Z",
                "category": "оплата за заказ"
            },
            {
                "nameDeal": "Расход",
                "nameWhoGive": "Усова Наталья",
                "nameWhoTake": "Кузнецов Сергей",
                "summ": 500,
                "comment": "Выдано на покупку расходных материалов",
                "date": "2019-01-21T23:02:52.910Z",
                "category": "подотчет"
            },
            {
                "nameDeal": "Расход",
                "nameWhoGive": "Усова Наталья",
                "nameWhoTake": "Колпаков Иван",
                "summ": 750,
                "comment": "Выдано на отправку заказа в Казань",
                "date": "2019-01-21T23:03:53.313Z",
                "category": "подотчет"
            },
            {
                "nameDeal": "Приход",
                "nameWhoGive": "Усова Наталья",
                "nameWhoTake": "ООО Биан-Принт",
                "summ": 3800,
                "comment": "за заказ №232",
                "date": "2019-01-21T23:05:50.593Z",
                "category": "оплата за заказ"
            },
            {
                "nameDeal": "Приход",
                "nameWhoGive": "Усова Наталья",
                "nameWhoTake": "Кузнецов Сергей",
                "summ": 123,
                "comment": "сдача после покупки расходных материалов",
                "date": "2019-01-21T23:07:11.848Z",
                "category": "возврат подотчетных"
            },
            {
                "nameDeal": "Расход",
                "nameWhoGive": "Люльков Андрей",
                "nameWhoTake": "Колпаков Иван",
                "summ": 600,
                "comment": "на бензин",
                "date": "2019-01-21T23:07:51.393Z",
                "category": "подотчет"
            }
        ],
        "categoriesPlus": [
            "оплата за заказ",
            "возврат подотчетных",
            "внесение наличных",
            "на нужды"
        ],
        "categoriesMinus": [
            "заработная плата",
            "подотчет",
            "изъятие наличных",
            "прочее"
        ]
    }
]